{"assets":{"AFB776B5851A6509A59A66233CB0FBCB":{"type":"texture","index":2,"assetRequest":{"type":"slide","state":"contents","slide":"none"},"url":{"native":"assets\/754C12B6-D933-497D-A322-177B04D21128.pdf"},"width":770,"height":67},"F3F263C7AEB6F14214956C86E2AD6C55":{"type":"texture","index":6,"assetRequest":{"type":"slide","state":"contents","slide":"none"},"url":{"native":"assets\/754C12B6-D933-497D-A322-177B04D21128.pdf"},"width":1024,"height":768},"0F6E5ED3ECD8814DF8BD76155269676F":{"type":"texture","index":3,"assetRequest":{"type":"slide","state":"contents","slide":"none"},"url":{"native":"assets\/754C12B6-D933-497D-A322-177B04D21128.pdf"},"width":1026,"height":538},"2A72BCFA5ADF195EA09004EC703E5E19":{"type":"texture","index":1,"assetRequest":{"type":"slide","state":"contents","slide":"none"},"url":{"native":"assets\/754C12B6-D933-497D-A322-177B04D21128.pdf"},"width":323,"height":31},"DB8451458D98EFA7506DBEBC2B1323F0":{"type":"texture","index":0,"assetRequest":{"type":"slide","state":"contents","slide":"none"},"url":{"native":"assets\/754C12B6-D933-497D-A322-177B04D21128.pdf"},"width":1024,"height":768},"6345D242F01F6EE924A7B6716E1D7571":{"type":"texture","index":7,"assetRequest":{"type":"slide","state":"contents","slide":"none"},"url":{"native":"assets\/754C12B6-D933-497D-A322-177B04D21128.pdf"},"width":1024,"height":768},"F780E9C426CC6B78A0B5C7E52CEB438A":{"type":"texture","index":4,"assetRequest":{"type":"slide","state":"contents","slide":"none"},"url":{"native":"assets\/754C12B6-D933-497D-A322-177B04D21128.pdf"},"width":304,"height":98},"C04CCF3DB57FC5679019C2E28D9A55E3":{"type":"texture","index":5,"assetRequest":{"type":"slide","state":"contents","slide":"none"},"url":{"native":"assets\/754C12B6-D933-497D-A322-177B04D21128.pdf"},"width":291,"height":296}},"events":[{"effects":[{"beginTime":0,"baseLayer":{"animations":[],"initialState":{"affineTransform":[1,0,0,1,0,0],"masksToBounds":false,"rotation":0,"scale":1,"position":{"pointX":520.294921875,"pointY":117.0625},"width":304,"sublayerTransform":[1,0,0,0,0,1,0,0,0,0,1,0,0,0,0,1],"contentsRect":{"y":0,"x":0,"width":1,"height":1},"opacity":1,"edgeAntialiasingMask":251658240,"height":98,"hidden":false,"anchorPoint":{"pointX":0.5,"pointY":0.5}},"objectID":"899792C3-C690-44C9-9B44-C6F0B230F76A","layers":[{"animations":[],"initialState":{"affineTransform":[1,0,0,1,0,0],"masksToBounds":false,"rotation":0,"scale":1,"position":{"pointX":143.705078125,"pointY":315.9375},"width":304,"sublayerTransform":[1,0,0,0,0,1,0,0,0,0,1,-0.00049229876906403734,0,0,0,1],"contentsRect":{"y":0,"x":0,"width":1,"height":1},"opacity":1,"edgeAntialiasingMask":251658240,"height":98,"hidden":false,"anchorPoint":{"pointX":0.47271407277960525,"pointY":3.2238520408163267}},"layers":[{"animations":[{"timeOffset":0,"beginTime":1e-100,"repeatCount":0,"animations":[{"timeOffset":0,"from":{"scalar":true},"beginTime":0,"repeatCount":0,"fillMode":"both","property":"hidden","autoreverses":false,"duration":0.0001,"to":{"scalar":false}},{"timeOffset":0,"from":{"scalar":false},"beginTime":0.0001,"repeatCount":0,"fillMode":"forwards","property":"hidden","autoreverses":false,"duration":0.0099000000000000008,"to":{"scalar":false}}],"fillMode":"both","autoreverses":false,"duration":0.01}],"layers":[],"texturedRectangle":{"singleTextureOpacity":1,"textXHeight":0,"shapePath":{"lineWidth":1,"flatness":0.59999999999999998,"lineCapStyle":0,"elements":[{"type":"MoveToPoint","points":[[2.294921875,89.16893196105957]]},{"type":"AddLine","points":[[2.294921875,8.3764476776123047]]},{"type":"AddCurve","points":[[2.294921875,4.8893506640374795],[5.1217725390374653,2.0625],[8.6088695526123047,2.0625]]},{"type":"AddLine","points":[[295.2817554473877,2.0625]]},{"type":"AddCurve","points":[[298.76885246096253,2.0625],[301.595703125,4.8893506640374795],[301.595703125,8.3764476776123047]]},{"type":"AddLine","points":[[301.595703125,89.16893196105957]]},{"type":"AddCurve","points":[[301.595703125,92.65602897463441],[298.76885246096253,95.482879638671875],[295.2817554473877,95.482879638671875]]},{"type":"AddLine","points":[[8.6088695526123047,95.482879638671903]]},{"type":"AddCurve","points":[[5.1217725390374653,95.482879638671903],[2.294921875,92.65602897463441],[2.294921875,89.168931961059599]]},{"type":"CloseSubpath"},{"type":"MoveToPoint","points":[[2.294921875,89.16893196105957]]}],"windingRule":0,"lineJoinStyle":0,"miterLimit":10},"isBackgroundTexture":true,"textBaseline":0,"isVerticalText":false,"textureType":5},"initialState":{"affineTransform":[1,0,0,1,0,0],"masksToBounds":false,"rotation":0,"scale":1,"position":{"pointX":150.705078125,"pointY":47.9375},"width":304,"sublayerTransform":[1,0,0,0,0,1,0,0,0,0,1,0,0,0,0,1],"contentsRect":{"y":0,"x":0,"width":1,"height":1},"opacity":1,"edgeAntialiasingMask":0,"height":98,"hidden":true,"anchorPoint":{"pointX":0.5,"pointY":0.5}},"texture":"F780E9C426CC6B78A0B5C7E52CEB438A"}]}]},"effects":[],"duration":0.01,"type":"buildIn","attributes":{"direction":0},"name":"apple:bc-appear","objectID":"899792C3-C690-44C9-9B44-C6F0B230F76A"}],"automaticPlay":false,"hyperlinks":[],"accessibility":[{"text":"pasted-image.tiff","targetRectangle":{"y":89.053337097167969,"x":0,"width":1024,"height":535.893310546875}},{"text":"Here’s another example:","targetRectangle":{"y":30,"x":349.15999999999997,"width":325.68000000000006,"height":36}}],"baseLayer":{"animations":[],"initialState":{"affineTransform":[1,0,0,1,0,0],"masksToBounds":false,"rotation":0,"scale":1,"position":{"pointX":512,"pointY":384},"width":1024,"sublayerTransform":[1,0,0,0,0,1,0,0,0,0,1,0,0,0,0,1],"contentsRect":{"y":0,"x":0,"width":1,"height":1},"opacity":1,"edgeAntialiasingMask":251658240,"height":768,"hidden":false,"anchorPoint":{"pointX":0.5,"pointY":0.5}},"layers":[{"animations":[],"initialState":{"affineTransform":[1,0,0,1,0,0],"masksToBounds":false,"rotation":0,"scale":1,"position":{"pointX":512,"pointY":384},"width":1024,"sublayerTransform":[1,0,0,0,0,1,0,0,0,0,1,0,0,0,0,1],"contentsRect":{"y":0,"x":0,"width":1,"height":1},"opacity":1,"edgeAntialiasingMask":251658240,"height":768,"hidden":false,"anchorPoint":{"pointX":0.5,"pointY":0.5}},"layers":[{"animations":[],"initialState":{"affineTransform":[1,0,0,1,0,0],"masksToBounds":false,"rotation":0,"scale":1,"position":{"pointX":512,"pointY":384},"width":1024,"sublayerTransform":[1,0,0,0,0,1,0,0,0,0,1,0,0,0,0,1],"contentsRect":{"y":0,"x":0,"width":1,"height":1},"opacity":1,"edgeAntialiasingMask":251658240,"height":768,"hidden":false,"anchorPoint":{"pointX":0.5,"pointY":0.5}},"layers":[{"animations":[],"layers":[],"texturedRectangle":{"isBackgroundTexture":true,"singleTextureOpacity":1,"textureType":1,"textBaseline":0,"textXHeight":0,"isVerticalText":false},"initialState":{"affineTransform":[1,0,0,1,0,0],"masksToBounds":false,"rotation":0,"scale":1,"position":{"pointX":512,"pointY":384},"width":1024,"sublayerTransform":[1,0,0,0,0,1,0,0,0,0,1,0,0,0,0,1],"contentsRect":{"y":0,"x":0,"width":1,"height":1},"opacity":1,"edgeAntialiasingMask":0,"height":768,"hidden":false,"anchorPoint":{"pointX":0.5,"pointY":0.5}},"texture":"DB8451458D98EFA7506DBEBC2B1323F0"}]}]},{"animations":[],"initialState":{"affineTransform":[1,0,0,1,0,0],"masksToBounds":false,"rotation":0,"scale":1,"position":{"pointX":512,"pointY":384},"width":1024,"sublayerTransform":[1,0,0,0,0,1,0,0,0,0,1,0,0,0,0,1],"contentsRect":{"y":0,"x":0,"width":1,"height":1},"opacity":1,"edgeAntialiasingMask":251658240,"height":768,"hidden":false,"anchorPoint":{"pointX":0.5,"pointY":0.5}},"layers":[{"animations":[],"initialState":{"affineTransform":[1,0,0,1,0,0],"masksToBounds":false,"rotation":0,"scale":1,"position":{"pointX":261.5,"pointY":-66.5},"width":323,"sublayerTransform":[1,0,0,0,0,1,0,0,0,0,1,0,0,0,0,1],"contentsRect":{"y":0,"x":0,"width":1,"height":1},"opacity":1,"edgeAntialiasingMask":251658240,"height":31,"hidden":false,"anchorPoint":{"pointX":0.5,"pointY":0.5}},"layers":[{"animations":[],"layers":[],"texturedRectangle":{"singleTextureOpacity":1,"textXHeight":0.50709677419354837,"textBaseline":0.74516542496219762,"isBackgroundTexture":true,"isVerticalText":false,"textColor":[1,1,1,1],"textureType":6},"initialState":{"affineTransform":[1,0,0,1,0,0],"masksToBounds":false,"rotation":0,"scale":1,"position":{"pointX":411.5,"pointY":133.5},"width":323,"sublayerTransform":[1,0,0,0,0,1,0,0,0,0,1,0,0,0,0,1],"contentsRect":{"y":0,"x":0,"width":1,"height":1},"opacity":1,"edgeAntialiasingMask":0,"height":31,"hidden":false,"anchorPoint":{"pointX":0.5,"pointY":0.5}},"texture":"2A72BCFA5ADF195EA09004EC703E5E19"}]}]},{"animations":[],"initialState":{"affineTransform":[1,0,0,1,0,0],"masksToBounds":false,"rotation":0,"scale":1,"position":{"pointX":512,"pointY":384},"width":1024,"sublayerTransform":[1,0,0,0,0,1,0,0,0,0,1,0,0,0,0,1],"contentsRect":{"y":0,"x":0,"width":1,"height":1},"opacity":1,"edgeAntialiasingMask":251658240,"height":768,"hidden":false,"anchorPoint":{"pointX":0.5,"pointY":0.5}},"layers":[{"animations":[],"initialState":{"affineTransform":[1,0,0,1,0,0],"masksToBounds":false,"rotation":0,"scale":1,"position":{"pointX":485,"pointY":599.5},"width":770,"sublayerTransform":[1,0,0,0,0,1,0,0,0,0,1,0,0,0,0,1],"contentsRect":{"y":0,"x":0,"width":1,"height":1},"opacity":1,"edgeAntialiasingMask":251658240,"height":67,"hidden":false,"anchorPoint":{"pointX":0.5,"pointY":0.5}},"objectID":"02F60865-BBBC-4EBF-B4E6-D436A975F95A","layers":[{"animations":[],"layers":[],"texturedRectangle":{"singleTextureOpacity":1,"textXHeight":0.23462686567164179,"textBaseline":0.88209146528101678,"isBackgroundTexture":true,"isVerticalText":false,"textColor":[1,1,1,1],"textureType":6},"initialState":{"affineTransform":[1,0,0,1,0,0],"masksToBounds":false,"rotation":0,"scale":1,"position":{"pointX":411,"pointY":133.5},"width":770,"sublayerTransform":[1,0,0,0,0,1,0,0,0,0,1,0,0,0,0,1],"contentsRect":{"y":0,"x":0,"width":1,"height":1},"opacity":1,"edgeAntialiasingMask":0,"height":67,"hidden":true,"anchorPoint":{"pointX":0.5,"pointY":0.5}},"texture":"AFB776B5851A6509A59A66233CB0FBCB"}]}]},{"animations":[],"initialState":{"affineTransform":[1,0,0,1,0,0],"masksToBounds":false,"rotation":0,"scale":1,"position":{"pointX":512,"pointY":384},"width":1024,"sublayerTransform":[1,0,0,0,0,1,0,0,0,0,1,0,0,0,0,1],"contentsRect":{"y":0,"x":0,"width":1,"height":1},"opacity":1,"edgeAntialiasingMask":251658240,"height":768,"hidden":false,"anchorPoint":{"pointX":0.5,"pointY":0.5}},"layers":[{"animations":[],"initialState":{"affineTransform":[1,0,0,1,0,0],"masksToBounds":false,"rotation":0,"scale":1,"position":{"pointX":513,"pointY":358.05333709716797},"width":1026,"sublayerTransform":[1,0,0,0,0,1,0,0,0,0,1,0,0,0,0,1],"contentsRect":{"y":0,"x":0,"width":1,"height":1},"opacity":1,"edgeAntialiasingMask":251658240,"height":538,"hidden":false,"anchorPoint":{"pointX":0.5,"pointY":0.5}},"layers":[{"animations":[],"layers":[],"texturedRectangle":{"isBackgroundTexture":true,"singleTextureOpacity":1,"textureType":5,"textBaseline":0,"textXHeight":0,"isVerticalText":false},"initialState":{"affineTransform":[1,0,0,1,0,0],"masksToBounds":false,"rotation":0,"scale":1,"position":{"pointX":512,"pointY":267.94666290283203},"width":1026,"sublayerTransform":[1,0,0,0,0,1,0,0,0,0,1,0,0,0,0,1],"contentsRect":{"y":0,"x":0,"width":1,"height":1},"opacity":1,"edgeAntialiasingMask":0,"height":538,"hidden":false,"anchorPoint":{"pointX":0.5,"pointY":0.5}},"texture":"0F6E5ED3ECD8814DF8BD76155269676F"}]}]},{"animations":[],"initialState":{"affineTransform":[1,0,0,1,0,0],"masksToBounds":false,"rotation":0,"scale":1,"position":{"pointX":512,"pointY":384},"width":1024,"sublayerTransform":[1,0,0,0,0,1,0,0,0,0,1,0,0,0,0,1],"contentsRect":{"y":0,"x":0,"width":1,"height":1},"opacity":1,"edgeAntialiasingMask":251658240,"height":768,"hidden":false,"anchorPoint":{"pointX":0.5,"pointY":0.5}},"layers":[{"animations":[],"initialState":{"affineTransform":[1,0,0,1,0,0],"masksToBounds":false,"rotation":0,"scale":1,"position":{"pointX":520.294921875,"pointY":117.0625},"width":304,"sublayerTransform":[1,0,0,0,0,1,0,0,0,0,1,0,0,0,0,1],"contentsRect":{"y":0,"x":0,"width":1,"height":1},"opacity":1,"edgeAntialiasingMask":251658240,"height":98,"hidden":false,"anchorPoint":{"pointX":0.5,"pointY":0.5}},"objectID":"899792C3-C690-44C9-9B44-C6F0B230F76A","layers":[{"animations":[],"layers":[],"texturedRectangle":{"singleTextureOpacity":1,"textXHeight":0,"shapePath":{"lineWidth":1,"flatness":0.59999999999999998,"lineCapStyle":0,"elements":[{"type":"MoveToPoint","points":[[2.294921875,89.16893196105957]]},{"type":"AddLine","points":[[2.294921875,8.3764476776123047]]},{"type":"AddCurve","points":[[2.294921875,4.8893506640374795],[5.1217725390374653,2.0625],[8.6088695526123047,2.0625]]},{"type":"AddLine","points":[[295.2817554473877,2.0625]]},{"type":"AddCurve","points":[[298.76885246096253,2.0625],[301.595703125,4.8893506640374795],[301.595703125,8.3764476776123047]]},{"type":"AddLine","points":[[301.595703125,89.16893196105957]]},{"type":"AddCurve","points":[[301.595703125,92.65602897463441],[298.76885246096253,95.482879638671875],[295.2817554473877,95.482879638671875]]},{"type":"AddLine","points":[[8.6088695526123047,95.482879638671903]]},{"type":"AddCurve","points":[[5.1217725390374653,95.482879638671903],[2.294921875,92.65602897463441],[2.294921875,89.168931961059599]]},{"type":"CloseSubpath"},{"type":"MoveToPoint","points":[[2.294921875,89.16893196105957]]}],"windingRule":0,"lineJoinStyle":0,"miterLimit":10},"isBackgroundTexture":true,"textBaseline":0,"isVerticalText":false,"textureType":5},"initialState":{"affineTransform":[1,0,0,1,0,0],"masksToBounds":false,"rotation":0,"scale":1,"position":{"pointX":150.705078125,"pointY":47.9375},"width":304,"sublayerTransform":[1,0,0,0,0,1,0,0,0,0,1,0,0,0,0,1],"contentsRect":{"y":0,"x":0,"width":1,"height":1},"opacity":1,"edgeAntialiasingMask":0,"height":98,"hidden":true,"anchorPoint":{"pointX":0.5,"pointY":0.5}},"texture":"F780E9C426CC6B78A0B5C7E52CEB438A"}]}]},{"animations":[],"initialState":{"affineTransform":[1,0,0,1,0,0],"masksToBounds":false,"rotation":0,"scale":1,"position":{"pointX":512,"pointY":384},"width":1024,"sublayerTransform":[1,0,0,0,0,1,0,0,0,0,1,0,0,0,0,1],"contentsRect":{"y":0,"x":0,"width":1,"height":1},"opacity":1,"edgeAntialiasingMask":251658240,"height":768,"hidden":false,"anchorPoint":{"pointX":0.5,"pointY":0.5}},"layers":[{"animations":[],"initialState":{"affineTransform":[1,0,0,1,0,0],"masksToBounds":false,"rotation":0,"scale":1,"position":{"pointX":399.375,"pointY":566.79296875},"width":291,"sublayerTransform":[1,0,0,0,0,1,0,0,0,0,1,0,0,0,0,1],"contentsRect":{"y":0,"x":0,"width":1,"height":1},"opacity":1,"edgeAntialiasingMask":251658240,"height":296,"hidden":false,"anchorPoint":{"pointX":0.5,"pointY":0.5}},"objectID":"BD0FFA7C-F975-43D8-854D-C23DF0F17905","layers":[{"animations":[],"layers":[],"texturedRectangle":{"singleTextureOpacity":1,"textXHeight":0,"shapePath":{"lineWidth":1,"flatness":0.59999999999999998,"lineCapStyle":0,"elements":[{"type":"MoveToPoint","points":[[9.1875,2.79296875]]},{"type":"AddCurve","points":[[5.7004028956095567,2.79296875],[2.875,5.6183716456095567],[2.875,9.10546875]]},{"type":"AddLine","points":[[2.875,102.88671875]]},{"type":"AddCurve","points":[[2.875,106.37381490071618],[5.7004028956095567,109.19921875],[9.1875,109.19921875]]},{"type":"AddLine","points":[[170.875,109.19921875]]},{"type":"AddLine","points":[[183.5,293.76171875]]},{"type":"AddLine","points":[[196.125,109.19921875]]},{"type":"AddLine","points":[[281.96875,109.19921875]]},{"type":"AddCurve","points":[[285.45583089192701,109.19920476277673],[288.28125,106.3738158543905],[288.28125,102.88671875]]},{"type":"AddLine","points":[[288.28125,9.10546875]]},{"type":"AddCurve","points":[[288.28128687540698,5.6183716456095567],[285.45584710439039,2.79296875],[281.96875,2.79296875]]},{"type":"AddLine","points":[[9.1875,2.79296875]]},{"type":"CloseSubpath"},{"type":"MoveToPoint","points":[[9.1875,2.79296875]]}],"windingRule":0,"lineJoinStyle":0,"miterLimit":10},"isBackgroundTexture":true,"textBaseline":0,"isVerticalText":false,"textureType":5},"initialState":{"affineTransform":[1,0,0,1,0,0],"masksToBounds":false,"rotation":0,"scale":1,"position":{"pointX":143.625,"pointY":146.20703125},"width":291,"sublayerTransform":[1,0,0,0,0,1,0,0,0,0,1,0,0,0,0,1],"contentsRect":{"y":0,"x":0,"width":1,"height":1},"opacity":1,"edgeAntialiasingMask":0,"height":296,"hidden":true,"anchorPoint":{"pointX":0.5,"pointY":0.5}},"texture":"C04CCF3DB57FC5679019C2E28D9A55E3"}]}]}]}},{"effects":[{"beginTime":0,"baseLayer":{"animations":[],"initialState":{"affineTransform":[1,0,0,1,0,0],"masksToBounds":false,"rotation":0,"scale":1,"position":{"pointX":485,"pointY":599.5},"width":770,"sublayerTransform":[1,0,0,0,0,1,0,0,0,0,1,0,0,0,0,1],"contentsRect":{"y":0,"x":0,"width":1,"height":1},"opacity":1,"edgeAntialiasingMask":251658240,"height":67,"hidden":false,"anchorPoint":{"pointX":0.5,"pointY":0.5}},"objectID":"02F60865-BBBC-4EBF-B4E6-D436A975F95A","layers":[{"animations":[],"initialState":{"affineTransform":[1,0,0,1,0,0],"masksToBounds":false,"rotation":0,"scale":1,"position":{"pointX":412,"pointY":-182},"width":770,"sublayerTransform":[1,0,0,0,0,1,0,0,0,0,1,-0.00049229876906403734,0,0,0,1],"contentsRect":{"y":0,"x":0,"width":1,"height":1},"opacity":1,"edgeAntialiasingMask":251658240,"height":67,"hidden":false,"anchorPoint":{"pointX":0.53506493506493502,"pointY":-2.716417910447761}},"layers":[{"animations":[{"timeOffset":0,"beginTime":1e-100,"repeatCount":0,"animations":[{"timeOffset":0,"from":{"scalar":true},"beginTime":0,"repeatCount":0,"fillMode":"both","property":"hidden","autoreverses":false,"duration":0.0001,"to":{"scalar":false}},{"timeOffset":0,"from":{"scalar":false},"beginTime":0.0001,"repeatCount":0,"fillMode":"forwards","property":"hidden","autoreverses":false,"duration":0.0099000000000000008,"to":{"scalar":false}}],"fillMode":"both","autoreverses":false,"duration":0.01}],"layers":[],"texturedRectangle":{"singleTextureOpacity":1,"textXHeight":0.23462686567164179,"textBaseline":0.88209146528101678,"isBackgroundTexture":true,"isVerticalText":false,"textColor":[1,1,1,1],"textureType":6},"initialState":{"affineTransform":[1,0,0,1,0,0],"masksToBounds":false,"rotation":0,"scale":1,"position":{"pointX":411,"pointY":133.5},"width":770,"sublayerTransform":[1,0,0,0,0,1,0,0,0,0,1,0,0,0,0,1],"contentsRect":{"y":0,"x":0,"width":1,"height":1},"opacity":1,"edgeAntialiasingMask":0,"height":67,"hidden":true,"anchorPoint":{"pointX":0.5,"pointY":0.5}},"texture":"AFB776B5851A6509A59A66233CB0FBCB"}]}]},"effects":[],"duration":0.01,"type":"buildIn","attributes":{"direction":0},"name":"apple:bc-appear","objectID":"02F60865-BBBC-4EBF-B4E6-D436A975F95A"}],"automaticPlay":false,"hyperlinks":[],"accessibility":[{"text":"pasted-image.tiff","targetRectangle":{"y":89.053337097167969,"x":0,"width":1024,"height":535.893310546875}},{"text":"Here’s another example:","targetRectangle":{"y":30,"x":349.15999999999997,"width":325.68000000000006,"height":36}}],"baseLayer":{"animations":[],"initialState":{"affineTransform":[1,0,0,1,0,0],"masksToBounds":false,"rotation":0,"scale":1,"position":{"pointX":512,"pointY":384},"width":1024,"sublayerTransform":[1,0,0,0,0,1,0,0,0,0,1,0,0,0,0,1],"contentsRect":{"y":0,"x":0,"width":1,"height":1},"opacity":1,"edgeAntialiasingMask":251658240,"height":768,"hidden":false,"anchorPoint":{"pointX":0.5,"pointY":0.5}},"layers":[{"animations":[],"initialState":{"affineTransform":[1,0,0,1,0,0],"masksToBounds":false,"rotation":0,"scale":1,"position":{"pointX":512,"pointY":384},"width":1024,"sublayerTransform":[1,0,0,0,0,1,0,0,0,0,1,0,0,0,0,1],"contentsRect":{"y":0,"x":0,"width":1,"height":1},"opacity":1,"edgeAntialiasingMask":251658240,"height":768,"hidden":false,"anchorPoint":{"pointX":0.5,"pointY":0.5}},"layers":[{"animations":[],"initialState":{"affineTransform":[1,0,0,1,0,0],"masksToBounds":false,"rotation":0,"scale":1,"position":{"pointX":512,"pointY":384},"width":1024,"sublayerTransform":[1,0,0,0,0,1,0,0,0,0,1,0,0,0,0,1],"contentsRect":{"y":0,"x":0,"width":1,"height":1},"opacity":1,"edgeAntialiasingMask":251658240,"height":768,"hidden":false,"anchorPoint":{"pointX":0.5,"pointY":0.5}},"layers":[{"animations":[],"layers":[],"texturedRectangle":{"isBackgroundTexture":true,"singleTextureOpacity":1,"textureType":1,"textBaseline":0,"textXHeight":0,"isVerticalText":false},"initialState":{"affineTransform":[1,0,0,1,0,0],"masksToBounds":false,"rotation":0,"scale":1,"position":{"pointX":512,"pointY":384},"width":1024,"sublayerTransform":[1,0,0,0,0,1,0,0,0,0,1,0,0,0,0,1],"contentsRect":{"y":0,"x":0,"width":1,"height":1},"opacity":1,"edgeAntialiasingMask":0,"height":768,"hidden":false,"anchorPoint":{"pointX":0.5,"pointY":0.5}},"texture":"DB8451458D98EFA7506DBEBC2B1323F0"}]}]},{"animations":[],"initialState":{"affineTransform":[1,0,0,1,0,0],"masksToBounds":false,"rotation":0,"scale":1,"position":{"pointX":512,"pointY":384},"width":1024,"sublayerTransform":[1,0,0,0,0,1,0,0,0,0,1,0,0,0,0,1],"contentsRect":{"y":0,"x":0,"width":1,"height":1},"opacity":1,"edgeAntialiasingMask":251658240,"height":768,"hidden":false,"anchorPoint":{"pointX":0.5,"pointY":0.5}},"layers":[{"animations":[],"initialState":{"affineTransform":[1,0,0,1,0,0],"masksToBounds":false,"rotation":0,"scale":1,"position":{"pointX":261.5,"pointY":-66.5},"width":323,"sublayerTransform":[1,0,0,0,0,1,0,0,0,0,1,0,0,0,0,1],"contentsRect":{"y":0,"x":0,"width":1,"height":1},"opacity":1,"edgeAntialiasingMask":251658240,"height":31,"hidden":false,"anchorPoint":{"pointX":0.5,"pointY":0.5}},"layers":[{"animations":[],"layers":[],"texturedRectangle":{"singleTextureOpacity":1,"textXHeight":0.50709677419354837,"textBaseline":0.74516542496219762,"isBackgroundTexture":true,"isVerticalText":false,"textColor":[1,1,1,1],"textureType":6},"initialState":{"affineTransform":[1,0,0,1,0,0],"masksToBounds":false,"rotation":0,"scale":1,"position":{"pointX":411.5,"pointY":133.5},"width":323,"sublayerTransform":[1,0,0,0,0,1,0,0,0,0,1,0,0,0,0,1],"contentsRect":{"y":0,"x":0,"width":1,"height":1},"opacity":1,"edgeAntialiasingMask":0,"height":31,"hidden":false,"anchorPoint":{"pointX":0.5,"pointY":0.5}},"texture":"2A72BCFA5ADF195EA09004EC703E5E19"}]}]},{"animations":[],"initialState":{"affineTransform":[1,0,0,1,0,0],"masksToBounds":false,"rotation":0,"scale":1,"position":{"pointX":512,"pointY":384},"width":1024,"sublayerTransform":[1,0,0,0,0,1,0,0,0,0,1,0,0,0,0,1],"contentsRect":{"y":0,"x":0,"width":1,"height":1},"opacity":1,"edgeAntialiasingMask":251658240,"height":768,"hidden":false,"anchorPoint":{"pointX":0.5,"pointY":0.5}},"layers":[{"animations":[],"initialState":{"affineTransform":[1,0,0,1,0,0],"masksToBounds":false,"rotation":0,"scale":1,"position":{"pointX":485,"pointY":599.5},"width":770,"sublayerTransform":[1,0,0,0,0,1,0,0,0,0,1,0,0,0,0,1],"contentsRect":{"y":0,"x":0,"width":1,"height":1},"opacity":1,"edgeAntialiasingMask":251658240,"height":67,"hidden":false,"anchorPoint":{"pointX":0.5,"pointY":0.5}},"objectID":"02F60865-BBBC-4EBF-B4E6-D436A975F95A","layers":[{"animations":[],"layers":[],"texturedRectangle":{"singleTextureOpacity":1,"textXHeight":0.23462686567164179,"textBaseline":0.88209146528101678,"isBackgroundTexture":true,"isVerticalText":false,"textColor":[1,1,1,1],"textureType":6},"initialState":{"affineTransform":[1,0,0,1,0,0],"masksToBounds":false,"rotation":0,"scale":1,"position":{"pointX":411,"pointY":133.5},"width":770,"sublayerTransform":[1,0,0,0,0,1,0,0,0,0,1,0,0,0,0,1],"contentsRect":{"y":0,"x":0,"width":1,"height":1},"opacity":1,"edgeAntialiasingMask":0,"height":67,"hidden":true,"anchorPoint":{"pointX":0.5,"pointY":0.5}},"texture":"AFB776B5851A6509A59A66233CB0FBCB"}]}]},{"animations":[],"initialState":{"affineTransform":[1,0,0,1,0,0],"masksToBounds":false,"rotation":0,"scale":1,"position":{"pointX":512,"pointY":384},"width":1024,"sublayerTransform":[1,0,0,0,0,1,0,0,0,0,1,0,0,0,0,1],"contentsRect":{"y":0,"x":0,"width":1,"height":1},"opacity":1,"edgeAntialiasingMask":251658240,"height":768,"hidden":false,"anchorPoint":{"pointX":0.5,"pointY":0.5}},"layers":[{"animations":[],"initialState":{"affineTransform":[1,0,0,1,0,0],"masksToBounds":false,"rotation":0,"scale":1,"position":{"pointX":513,"pointY":358.05333709716797},"width":1026,"sublayerTransform":[1,0,0,0,0,1,0,0,0,0,1,0,0,0,0,1],"contentsRect":{"y":0,"x":0,"width":1,"height":1},"opacity":1,"edgeAntialiasingMask":251658240,"height":538,"hidden":false,"anchorPoint":{"pointX":0.5,"pointY":0.5}},"layers":[{"animations":[],"layers":[],"texturedRectangle":{"isBackgroundTexture":true,"singleTextureOpacity":1,"textureType":5,"textBaseline":0,"textXHeight":0,"isVerticalText":false},"initialState":{"affineTransform":[1,0,0,1,0,0],"masksToBounds":false,"rotation":0,"scale":1,"position":{"pointX":512,"pointY":267.94666290283203},"width":1026,"sublayerTransform":[1,0,0,0,0,1,0,0,0,0,1,0,0,0,0,1],"contentsRect":{"y":0,"x":0,"width":1,"height":1},"opacity":1,"edgeAntialiasingMask":0,"height":538,"hidden":false,"anchorPoint":{"pointX":0.5,"pointY":0.5}},"texture":"0F6E5ED3ECD8814DF8BD76155269676F"}]}]},{"animations":[],"initialState":{"affineTransform":[1,0,0,1,0,0],"masksToBounds":false,"rotation":0,"scale":1,"position":{"pointX":512,"pointY":384},"width":1024,"sublayerTransform":[1,0,0,0,0,1,0,0,0,0,1,0,0,0,0,1],"contentsRect":{"y":0,"x":0,"width":1,"height":1},"opacity":1,"edgeAntialiasingMask":251658240,"height":768,"hidden":false,"anchorPoint":{"pointX":0.5,"pointY":0.5}},"layers":[{"animations":[],"initialState":{"affineTransform":[1,0,0,1,0,0],"masksToBounds":false,"rotation":0,"scale":1,"position":{"pointX":520.294921875,"pointY":117.0625},"width":304,"sublayerTransform":[1,0,0,0,0,1,0,0,0,0,1,0,0,0,0,1],"contentsRect":{"y":0,"x":0,"width":1,"height":1},"opacity":1,"edgeAntialiasingMask":251658240,"height":98,"hidden":false,"anchorPoint":{"pointX":0.5,"pointY":0.5}},"objectID":"899792C3-C690-44C9-9B44-C6F0B230F76A","layers":[{"animations":[],"layers":[],"texturedRectangle":{"singleTextureOpacity":1,"textXHeight":0,"shapePath":{"lineWidth":1,"flatness":0.59999999999999998,"lineCapStyle":0,"elements":[{"type":"MoveToPoint","points":[[2.294921875,89.16893196105957]]},{"type":"AddLine","points":[[2.294921875,8.3764476776123047]]},{"type":"AddCurve","points":[[2.294921875,4.8893506640374795],[5.1217725390374653,2.0625],[8.6088695526123047,2.0625]]},{"type":"AddLine","points":[[295.2817554473877,2.0625]]},{"type":"AddCurve","points":[[298.76885246096253,2.0625],[301.595703125,4.8893506640374795],[301.595703125,8.3764476776123047]]},{"type":"AddLine","points":[[301.595703125,89.16893196105957]]},{"type":"AddCurve","points":[[301.595703125,92.65602897463441],[298.76885246096253,95.482879638671875],[295.2817554473877,95.482879638671875]]},{"type":"AddLine","points":[[8.6088695526123047,95.482879638671903]]},{"type":"AddCurve","points":[[5.1217725390374653,95.482879638671903],[2.294921875,92.65602897463441],[2.294921875,89.168931961059599]]},{"type":"CloseSubpath"},{"type":"MoveToPoint","points":[[2.294921875,89.16893196105957]]}],"windingRule":0,"lineJoinStyle":0,"miterLimit":10},"isBackgroundTexture":true,"textBaseline":0,"isVerticalText":false,"textureType":5},"initialState":{"affineTransform":[1,0,0,1,0,0],"masksToBounds":false,"rotation":0,"scale":1,"position":{"pointX":150.705078125,"pointY":47.9375},"width":304,"sublayerTransform":[1,0,0,0,0,1,0,0,0,0,1,0,0,0,0,1],"contentsRect":{"y":0,"x":0,"width":1,"height":1},"opacity":1,"edgeAntialiasingMask":0,"height":98,"hidden":false,"anchorPoint":{"pointX":0.5,"pointY":0.5}},"texture":"F780E9C426CC6B78A0B5C7E52CEB438A"}]}]},{"animations":[],"initialState":{"affineTransform":[1,0,0,1,0,0],"masksToBounds":false,"rotation":0,"scale":1,"position":{"pointX":512,"pointY":384},"width":1024,"sublayerTransform":[1,0,0,0,0,1,0,0,0,0,1,0,0,0,0,1],"contentsRect":{"y":0,"x":0,"width":1,"height":1},"opacity":1,"edgeAntialiasingMask":251658240,"height":768,"hidden":false,"anchorPoint":{"pointX":0.5,"pointY":0.5}},"layers":[{"animations":[],"initialState":{"affineTransform":[1,0,0,1,0,0],"masksToBounds":false,"rotation":0,"scale":1,"position":{"pointX":399.375,"pointY":566.79296875},"width":291,"sublayerTransform":[1,0,0,0,0,1,0,0,0,0,1,0,0,0,0,1],"contentsRect":{"y":0,"x":0,"width":1,"height":1},"opacity":1,"edgeAntialiasingMask":251658240,"height":296,"hidden":false,"anchorPoint":{"pointX":0.5,"pointY":0.5}},"objectID":"BD0FFA7C-F975-43D8-854D-C23DF0F17905","layers":[{"animations":[],"layers":[],"texturedRectangle":{"singleTextureOpacity":1,"textXHeight":0,"shapePath":{"lineWidth":1,"flatness":0.59999999999999998,"lineCapStyle":0,"elements":[{"type":"MoveToPoint","points":[[9.1875,2.79296875]]},{"type":"AddCurve","points":[[5.7004028956095567,2.79296875],[2.875,5.6183716456095567],[2.875,9.10546875]]},{"type":"AddLine","points":[[2.875,102.88671875]]},{"type":"AddCurve","points":[[2.875,106.37381490071618],[5.7004028956095567,109.19921875],[9.1875,109.19921875]]},{"type":"AddLine","points":[[170.875,109.19921875]]},{"type":"AddLine","points":[[183.5,293.76171875]]},{"type":"AddLine","points":[[196.125,109.19921875]]},{"type":"AddLine","points":[[281.96875,109.19921875]]},{"type":"AddCurve","points":[[285.45583089192701,109.19920476277673],[288.28125,106.3738158543905],[288.28125,102.88671875]]},{"type":"AddLine","points":[[288.28125,9.10546875]]},{"type":"AddCurve","points":[[288.28128687540698,5.6183716456095567],[285.45584710439039,2.79296875],[281.96875,2.79296875]]},{"type":"AddLine","points":[[9.1875,2.79296875]]},{"type":"CloseSubpath"},{"type":"MoveToPoint","points":[[9.1875,2.79296875]]}],"windingRule":0,"lineJoinStyle":0,"miterLimit":10},"isBackgroundTexture":true,"textBaseline":0,"isVerticalText":false,"textureType":5},"initialState":{"affineTransform":[1,0,0,1,0,0],"masksToBounds":false,"rotation":0,"scale":1,"position":{"pointX":143.625,"pointY":146.20703125},"width":291,"sublayerTransform":[1,0,0,0,0,1,0,0,0,0,1,0,0,0,0,1],"contentsRect":{"y":0,"x":0,"width":1,"height":1},"opacity":1,"edgeAntialiasingMask":0,"height":296,"hidden":true,"anchorPoint":{"pointX":0.5,"pointY":0.5}},"texture":"C04CCF3DB57FC5679019C2E28D9A55E3"}]}]}]}},{"effects":[{"beginTime":0,"baseLayer":{"animations":[],"initialState":{"affineTransform":[1,0,0,1,0,0],"masksToBounds":false,"rotation":0,"scale":1,"position":{"pointX":399.375,"pointY":566.79296875},"width":291,"sublayerTransform":[1,0,0,0,0,1,0,0,0,0,1,0,0,0,0,1],"contentsRect":{"y":0,"x":0,"width":1,"height":1},"opacity":1,"edgeAntialiasingMask":251658240,"height":296,"hidden":false,"anchorPoint":{"pointX":0.5,"pointY":0.5}},"objectID":"BD0FFA7C-F975-43D8-854D-C23DF0F17905","layers":[{"animations":[],"initialState":{"affineTransform":[1,0,0,1,0,0],"masksToBounds":false,"rotation":0,"scale":1,"position":{"pointX":258.125,"pointY":-34.79296875},"width":291,"sublayerTransform":[1,0,0,0,0,1,0,0,0,0,1,-0.00049229876906403734,0,0,0,1],"contentsRect":{"y":0,"x":0,"width":1,"height":1},"opacity":1,"edgeAntialiasingMask":251658240,"height":296,"hidden":false,"anchorPoint":{"pointX":0.88702749140893467,"pointY":-0.1175438133445946}},"layers":[{"animations":[{"timeOffset":0,"beginTime":1e-100,"repeatCount":0,"animations":[{"timeOffset":0,"from":{"scalar":true},"beginTime":0,"repeatCount":0,"fillMode":"both","property":"hidden","autoreverses":false,"duration":0.0001,"to":{"scalar":false}},{"timeOffset":0,"from":{"scalar":false},"beginTime":0.0001,"repeatCount":0,"fillMode":"forwards","property":"hidden","autoreverses":false,"duration":0.0099000000000000008,"to":{"scalar":false}}],"fillMode":"both","autoreverses":false,"duration":0.01}],"layers":[],"texturedRectangle":{"singleTextureOpacity":1,"textXHeight":0,"shapePath":{"lineWidth":1,"flatness":0.59999999999999998,"lineCapStyle":0,"elements":[{"type":"MoveToPoint","points":[[9.1875,2.79296875]]},{"type":"AddCurve","points":[[5.7004028956095567,2.79296875],[2.875,5.6183716456095567],[2.875,9.10546875]]},{"type":"AddLine","points":[[2.875,102.88671875]]},{"type":"AddCurve","points":[[2.875,106.37381490071618],[5.7004028956095567,109.19921875],[9.1875,109.19921875]]},{"type":"AddLine","points":[[170.875,109.19921875]]},{"type":"AddLine","points":[[183.5,293.76171875]]},{"type":"AddLine","points":[[196.125,109.19921875]]},{"type":"AddLine","points":[[281.96875,109.19921875]]},{"type":"AddCurve","points":[[285.45583089192701,109.19920476277673],[288.28125,106.3738158543905],[288.28125,102.88671875]]},{"type":"AddLine","points":[[288.28125,9.10546875]]},{"type":"AddCurve","points":[[288.28128687540698,5.6183716456095567],[285.45584710439039,2.79296875],[281.96875,2.79296875]]},{"type":"AddLine","points":[[9.1875,2.79296875]]},{"type":"CloseSubpath"},{"type":"MoveToPoint","points":[[9.1875,2.79296875]]}],"windingRule":0,"lineJoinStyle":0,"miterLimit":10},"isBackgroundTexture":true,"textBaseline":0,"isVerticalText":false,"textureType":5},"initialState":{"affineTransform":[1,0,0,1,0,0],"masksToBounds":false,"rotation":0,"scale":1,"position":{"pointX":143.625,"pointY":146.20703125},"width":291,"sublayerTransform":[1,0,0,0,0,1,0,0,0,0,1,0,0,0,0,1],"contentsRect":{"y":0,"x":0,"width":1,"height":1},"opacity":1,"edgeAntialiasingMask":0,"height":296,"hidden":true,"anchorPoint":{"pointX":0.5,"pointY":0.5}},"texture":"C04CCF3DB57FC5679019C2E28D9A55E3"}]}]},"effects":[],"duration":0.01,"type":"buildIn","attributes":{"direction":0},"name":"apple:bc-appear","objectID":"BD0FFA7C-F975-43D8-854D-C23DF0F17905"}],"automaticPlay":false,"hyperlinks":[],"accessibility":[{"text":"For an image of 320 x 200 pixels = 64000 pixels at","targetRectangle":{"y":660,"x":173.61500000000007,"width":676.76999999999998,"height":36}},{"text":"24 bits per pixel = 1,536,000 bits to remember the image!","targetRectangle":{"y":696,"x":125.58500000000009,"width":772.82999999999993,"height":36}},{"text":"pasted-image.tiff","targetRectangle":{"y":89.053337097167969,"x":0,"width":1024,"height":535.893310546875}},{"text":"Here’s another example:","targetRectangle":{"y":30,"x":349.15999999999997,"width":325.68000000000006,"height":36}}],"baseLayer":{"animations":[],"initialState":{"affineTransform":[1,0,0,1,0,0],"masksToBounds":false,"rotation":0,"scale":1,"position":{"pointX":512,"pointY":384},"width":1024,"sublayerTransform":[1,0,0,0,0,1,0,0,0,0,1,0,0,0,0,1],"contentsRect":{"y":0,"x":0,"width":1,"height":1},"opacity":1,"edgeAntialiasingMask":251658240,"height":768,"hidden":false,"anchorPoint":{"pointX":0.5,"pointY":0.5}},"layers":[{"animations":[],"initialState":{"affineTransform":[1,0,0,1,0,0],"masksToBounds":false,"rotation":0,"scale":1,"position":{"pointX":512,"pointY":384},"width":1024,"sublayerTransform":[1,0,0,0,0,1,0,0,0,0,1,0,0,0,0,1],"contentsRect":{"y":0,"x":0,"width":1,"height":1},"opacity":1,"edgeAntialiasingMask":251658240,"height":768,"hidden":false,"anchorPoint":{"pointX":0.5,"pointY":0.5}},"layers":[{"animations":[],"initialState":{"affineTransform":[1,0,0,1,0,0],"masksToBounds":false,"rotation":0,"scale":1,"position":{"pointX":512,"pointY":384},"width":1024,"sublayerTransform":[1,0,0,0,0,1,0,0,0,0,1,0,0,0,0,1],"contentsRect":{"y":0,"x":0,"width":1,"height":1},"opacity":1,"edgeAntialiasingMask":251658240,"height":768,"hidden":false,"anchorPoint":{"pointX":0.5,"pointY":0.5}},"layers":[{"animations":[],"layers":[],"texturedRectangle":{"isBackgroundTexture":true,"singleTextureOpacity":1,"textureType":1,"textBaseline":0,"textXHeight":0,"isVerticalText":false},"initialState":{"affineTransform":[1,0,0,1,0,0],"masksToBounds":false,"rotation":0,"scale":1,"position":{"pointX":512,"pointY":384},"width":1024,"sublayerTransform":[1,0,0,0,0,1,0,0,0,0,1,0,0,0,0,1],"contentsRect":{"y":0,"x":0,"width":1,"height":1},"opacity":1,"edgeAntialiasingMask":0,"height":768,"hidden":false,"anchorPoint":{"pointX":0.5,"pointY":0.5}},"texture":"DB8451458D98EFA7506DBEBC2B1323F0"}]}]},{"animations":[],"initialState":{"affineTransform":[1,0,0,1,0,0],"masksToBounds":false,"rotation":0,"scale":1,"position":{"pointX":512,"pointY":384},"width":1024,"sublayerTransform":[1,0,0,0,0,1,0,0,0,0,1,0,0,0,0,1],"contentsRect":{"y":0,"x":0,"width":1,"height":1},"opacity":1,"edgeAntialiasingMask":251658240,"height":768,"hidden":false,"anchorPoint":{"pointX":0.5,"pointY":0.5}},"layers":[{"animations":[],"initialState":{"affineTransform":[1,0,0,1,0,0],"masksToBounds":false,"rotation":0,"scale":1,"position":{"pointX":261.5,"pointY":-66.5},"width":323,"sublayerTransform":[1,0,0,0,0,1,0,0,0,0,1,0,0,0,0,1],"contentsRect":{"y":0,"x":0,"width":1,"height":1},"opacity":1,"edgeAntialiasingMask":251658240,"height":31,"hidden":false,"anchorPoint":{"pointX":0.5,"pointY":0.5}},"layers":[{"animations":[],"layers":[],"texturedRectangle":{"singleTextureOpacity":1,"textXHeight":0.50709677419354837,"textBaseline":0.74516542496219762,"isBackgroundTexture":true,"isVerticalText":false,"textColor":[1,1,1,1],"textureType":6},"initialState":{"affineTransform":[1,0,0,1,0,0],"masksToBounds":false,"rotation":0,"scale":1,"position":{"pointX":411.5,"pointY":133.5},"width":323,"sublayerTransform":[1,0,0,0,0,1,0,0,0,0,1,0,0,0,0,1],"contentsRect":{"y":0,"x":0,"width":1,"height":1},"opacity":1,"edgeAntialiasingMask":0,"height":31,"hidden":false,"anchorPoint":{"pointX":0.5,"pointY":0.5}},"texture":"2A72BCFA5ADF195EA09004EC703E5E19"}]}]},{"animations":[],"initialState":{"affineTransform":[1,0,0,1,0,0],"masksToBounds":false,"rotation":0,"scale":1,"position":{"pointX":512,"pointY":384},"width":1024,"sublayerTransform":[1,0,0,0,0,1,0,0,0,0,1,0,0,0,0,1],"contentsRect":{"y":0,"x":0,"width":1,"height":1},"opacity":1,"edgeAntialiasingMask":251658240,"height":768,"hidden":false,"anchorPoint":{"pointX":0.5,"pointY":0.5}},"layers":[{"animations":[],"initialState":{"affineTransform":[1,0,0,1,0,0],"masksToBounds":false,"rotation":0,"scale":1,"position":{"pointX":485,"pointY":599.5},"width":770,"sublayerTransform":[1,0,0,0,0,1,0,0,0,0,1,0,0,0,0,1],"contentsRect":{"y":0,"x":0,"width":1,"height":1},"opacity":1,"edgeAntialiasingMask":251658240,"height":67,"hidden":false,"anchorPoint":{"pointX":0.5,"pointY":0.5}},"objectID":"02F60865-BBBC-4EBF-B4E6-D436A975F95A","layers":[{"animations":[],"layers":[],"texturedRectangle":{"singleTextureOpacity":1,"textXHeight":0.23462686567164179,"textBaseline":0.88209146528101678,"isBackgroundTexture":true,"isVerticalText":false,"textColor":[1,1,1,1],"textureType":6},"initialState":{"affineTransform":[1,0,0,1,0,0],"masksToBounds":false,"rotation":0,"scale":1,"position":{"pointX":411,"pointY":133.5},"width":770,"sublayerTransform":[1,0,0,0,0,1,0,0,0,0,1,0,0,0,0,1],"contentsRect":{"y":0,"x":0,"width":1,"height":1},"opacity":1,"edgeAntialiasingMask":0,"height":67,"hidden":false,"anchorPoint":{"pointX":0.5,"pointY":0.5}},"texture":"AFB776B5851A6509A59A66233CB0FBCB"}]}]},{"animations":[],"initialState":{"affineTransform":[1,0,0,1,0,0],"masksToBounds":false,"rotation":0,"scale":1,"position":{"pointX":512,"pointY":384},"width":1024,"sublayerTransform":[1,0,0,0,0,1,0,0,0,0,1,0,0,0,0,1],"contentsRect":{"y":0,"x":0,"width":1,"height":1},"opacity":1,"edgeAntialiasingMask":251658240,"height":768,"hidden":false,"anchorPoint":{"pointX":0.5,"pointY":0.5}},"layers":[{"animations":[],"initialState":{"affineTransform":[1,0,0,1,0,0],"masksToBounds":false,"rotation":0,"scale":1,"position":{"pointX":513,"pointY":358.05333709716797},"width":1026,"sublayerTransform":[1,0,0,0,0,1,0,0,0,0,1,0,0,0,0,1],"contentsRect":{"y":0,"x":0,"width":1,"height":1},"opacity":1,"edgeAntialiasingMask":251658240,"height":538,"hidden":false,"anchorPoint":{"pointX":0.5,"pointY":0.5}},"layers":[{"animations":[],"layers":[],"texturedRectangle":{"isBackgroundTexture":true,"singleTextureOpacity":1,"textureType":5,"textBaseline":0,"textXHeight":0,"isVerticalText":false},"initialState":{"affineTransform":[1,0,0,1,0,0],"masksToBounds":false,"rotation":0,"scale":1,"position":{"pointX":512,"pointY":267.94666290283203},"width":1026,"sublayerTransform":[1,0,0,0,0,1,0,0,0,0,1,0,0,0,0,1],"contentsRect":{"y":0,"x":0,"width":1,"height":1},"opacity":1,"edgeAntialiasingMask":0,"height":538,"hidden":false,"anchorPoint":{"pointX":0.5,"pointY":0.5}},"texture":"0F6E5ED3ECD8814DF8BD76155269676F"}]}]},{"animations":[],"initialState":{"affineTransform":[1,0,0,1,0,0],"masksToBounds":false,"rotation":0,"scale":1,"position":{"pointX":512,"pointY":384},"width":1024,"sublayerTransform":[1,0,0,0,0,1,0,0,0,0,1,0,0,0,0,1],"contentsRect":{"y":0,"x":0,"width":1,"height":1},"opacity":1,"edgeAntialiasingMask":251658240,"height":768,"hidden":false,"anchorPoint":{"pointX":0.5,"pointY":0.5}},"layers":[{"animations":[],"initialState":{"affineTransform":[1,0,0,1,0,0],"masksToBounds":false,"rotation":0,"scale":1,"position":{"pointX":520.294921875,"pointY":117.0625},"width":304,"sublayerTransform":[1,0,0,0,0,1,0,0,0,0,1,0,0,0,0,1],"contentsRect":{"y":0,"x":0,"width":1,"height":1},"opacity":1,"edgeAntialiasingMask":251658240,"height":98,"hidden":false,"anchorPoint":{"pointX":0.5,"pointY":0.5}},"objectID":"899792C3-C690-44C9-9B44-C6F0B230F76A","layers":[{"animations":[],"layers":[],"texturedRectangle":{"singleTextureOpacity":1,"textXHeight":0,"shapePath":{"lineWidth":1,"flatness":0.59999999999999998,"lineCapStyle":0,"elements":[{"type":"MoveToPoint","points":[[2.294921875,89.16893196105957]]},{"type":"AddLine","points":[[2.294921875,8.3764476776123047]]},{"type":"AddCurve","points":[[2.294921875,4.8893506640374795],[5.1217725390374653,2.0625],[8.6088695526123047,2.0625]]},{"type":"AddLine","points":[[295.2817554473877,2.0625]]},{"type":"AddCurve","points":[[298.76885246096253,2.0625],[301.595703125,4.8893506640374795],[301.595703125,8.3764476776123047]]},{"type":"AddLine","points":[[301.595703125,89.16893196105957]]},{"type":"AddCurve","points":[[301.595703125,92.65602897463441],[298.76885246096253,95.482879638671875],[295.2817554473877,95.482879638671875]]},{"type":"AddLine","points":[[8.6088695526123047,95.482879638671903]]},{"type":"AddCurve","points":[[5.1217725390374653,95.482879638671903],[2.294921875,92.65602897463441],[2.294921875,89.168931961059599]]},{"type":"CloseSubpath"},{"type":"MoveToPoint","points":[[2.294921875,89.16893196105957]]}],"windingRule":0,"lineJoinStyle":0,"miterLimit":10},"isBackgroundTexture":true,"textBaseline":0,"isVerticalText":false,"textureType":5},"initialState":{"affineTransform":[1,0,0,1,0,0],"masksToBounds":false,"rotation":0,"scale":1,"position":{"pointX":150.705078125,"pointY":47.9375},"width":304,"sublayerTransform":[1,0,0,0,0,1,0,0,0,0,1,0,0,0,0,1],"contentsRect":{"y":0,"x":0,"width":1,"height":1},"opacity":1,"edgeAntialiasingMask":0,"height":98,"hidden":false,"anchorPoint":{"pointX":0.5,"pointY":0.5}},"texture":"F780E9C426CC6B78A0B5C7E52CEB438A"}]}]},{"animations":[],"initialState":{"affineTransform":[1,0,0,1,0,0],"masksToBounds":false,"rotation":0,"scale":1,"position":{"pointX":512,"pointY":384},"width":1024,"sublayerTransform":[1,0,0,0,0,1,0,0,0,0,1,0,0,0,0,1],"contentsRect":{"y":0,"x":0,"width":1,"height":1},"opacity":1,"edgeAntialiasingMask":251658240,"height":768,"hidden":false,"anchorPoint":{"pointX":0.5,"pointY":0.5}},"layers":[{"animations":[],"initialState":{"affineTransform":[1,0,0,1,0,0],"masksToBounds":false,"rotation":0,"scale":1,"position":{"pointX":399.375,"pointY":566.79296875},"width":291,"sublayerTransform":[1,0,0,0,0,1,0,0,0,0,1,0,0,0,0,1],"contentsRect":{"y":0,"x":0,"width":1,"height":1},"opacity":1,"edgeAntialiasingMask":251658240,"height":296,"hidden":false,"anchorPoint":{"pointX":0.5,"pointY":0.5}},"objectID":"BD0FFA7C-F975-43D8-854D-C23DF0F17905","layers":[{"animations":[],"layers":[],"texturedRectangle":{"singleTextureOpacity":1,"textXHeight":0,"shapePath":{"lineWidth":1,"flatness":0.59999999999999998,"lineCapStyle":0,"elements":[{"type":"MoveToPoint","points":[[9.1875,2.79296875]]},{"type":"AddCurve","points":[[5.7004028956095567,2.79296875],[2.875,5.6183716456095567],[2.875,9.10546875]]},{"type":"AddLine","points":[[2.875,102.88671875]]},{"type":"AddCurve","points":[[2.875,106.37381490071618],[5.7004028956095567,109.19921875],[9.1875,109.19921875]]},{"type":"AddLine","points":[[170.875,109.19921875]]},{"type":"AddLine","points":[[183.5,293.76171875]]},{"type":"AddLine","points":[[196.125,109.19921875]]},{"type":"AddLine","points":[[281.96875,109.19921875]]},{"type":"AddCurve","points":[[285.45583089192701,109.19920476277673],[288.28125,106.3738158543905],[288.28125,102.88671875]]},{"type":"AddLine","points":[[288.28125,9.10546875]]},{"type":"AddCurve","points":[[288.28128687540698,5.6183716456095567],[285.45584710439039,2.79296875],[281.96875,2.79296875]]},{"type":"AddLine","points":[[9.1875,2.79296875]]},{"type":"CloseSubpath"},{"type":"MoveToPoint","points":[[9.1875,2.79296875]]}],"windingRule":0,"lineJoinStyle":0,"miterLimit":10},"isBackgroundTexture":true,"textBaseline":0,"isVerticalText":false,"textureType":5},"initialState":{"affineTransform":[1,0,0,1,0,0],"masksToBounds":false,"rotation":0,"scale":1,"position":{"pointX":143.625,"pointY":146.20703125},"width":291,"sublayerTransform":[1,0,0,0,0,1,0,0,0,0,1,0,0,0,0,1],"contentsRect":{"y":0,"x":0,"width":1,"height":1},"opacity":1,"edgeAntialiasingMask":0,"height":296,"hidden":true,"anchorPoint":{"pointX":0.5,"pointY":0.5}},"texture":"C04CCF3DB57FC5679019C2E28D9A55E3"}]}]}]}},{"effects":[{"beginTime":0,"baseLayer":{"animations":[],"initialState":{"affineTransform":[1,0,0,1,0,0],"masksToBounds":false,"rotation":0,"scale":1,"position":{"pointX":512,"pointY":384},"width":1024,"sublayerTransform":[1,0,0,0,0,1,0,0,0,0,1,0,0,0,0,1],"contentsRect":{"y":0,"x":0,"width":1,"height":1},"opacity":1,"edgeAntialiasingMask":251658240,"height":768,"hidden":false,"anchorPoint":{"pointX":0.5,"pointY":0.5}},"objectID":"0","layers":[{"animations":[],"initialState":{"affineTransform":[1,0,0,1,0,0],"masksToBounds":false,"rotation":0,"scale":1,"position":{"pointX":512,"pointY":384},"width":1024,"sublayerTransform":[1,0,0,0,0,1,0,0,0,0,1,-0.00049229876906403734,0,0,0,1],"contentsRect":{"y":0,"x":0,"width":1,"height":1},"opacity":1,"edgeAntialiasingMask":251658240,"height":768,"hidden":false,"anchorPoint":{"pointX":0.5,"pointY":0.5}},"layers":[{"animations":[],"layers":[],"texturedRectangle":{"isBackgroundTexture":false,"singleTextureOpacity":1,"textureType":0,"textBaseline":0,"textXHeight":0,"isVerticalText":false},"initialState":{"affineTransform":[1,0,0,1,0,0],"masksToBounds":false,"rotation":0,"scale":1,"position":{"pointX":512,"pointY":384},"width":1024,"sublayerTransform":[1,0,0,0,0,1,0,0,0,0,1,0,0,0,0,1],"contentsRect":{"y":0,"x":0,"width":1,"height":1},"opacity":1,"edgeAntialiasingMask":0,"height":768,"hidden":false,"anchorPoint":{"pointX":0.5,"pointY":0.5}},"texture":"6345D242F01F6EE924A7B6716E1D7571"},{"animations":[{"timeOffset":0,"from":{"scalar":false},"beginTime":0,"repeatCount":0,"fillMode":"both","property":"hidden","autoreverses":false,"duration":0.01,"to":{"scalar":true}}],"layers":[],"texturedRectangle":{"isBackgroundTexture":false,"singleTextureOpacity":1,"textureType":0,"textBaseline":0,"textXHeight":0,"isVerticalText":false},"initialState":{"affineTransform":[1,0,0,1,0,0],"masksToBounds":false,"rotation":0,"scale":1,"position":{"pointX":512,"pointY":384},"width":1024,"sublayerTransform":[1,0,0,0,0,1,0,0,0,0,1,0,0,0,0,1],"contentsRect":{"y":0,"x":0,"width":1,"height":1},"opacity":1,"edgeAntialiasingMask":0,"height":768,"hidden":false,"anchorPoint":{"pointX":0.5,"pointY":0.5}},"texture":"F3F263C7AEB6F14214956C86E2AD6C55"}]}]},"effects":[],"duration":0.01,"type":"transition","attributes":{"direction":0},"name":"none","objectID":"0"}],"automaticPlay":false,"hyperlinks":[],"accessibility":[{"text":"For an image of 320 x 200 pixels = 64000 pixels at","targetRectangle":{"y":660,"x":173.61500000000007,"width":676.76999999999998,"height":36}},{"text":"24 bits per pixel = 1,536,000 bits to remember the image!","targetRectangle":{"y":696,"x":125.58500000000009,"width":772.82999999999993,"height":36}},{"text":"You pay a price for that quality: it takes WAY more total bits to remember the image!","targetRectangle":{"y":436.91796875,"x":260.48812499999997,"width":279.74000000000001,"height":72}},{"text":"pasted-image.tiff","targetRectangle":{"y":89.053337097167969,"x":0,"width":1024,"height":535.893310546875}},{"text":"Here’s another example:","targetRectangle":{"y":30,"x":349.15999999999997,"width":325.68000000000006,"height":36}}],"baseLayer":{"animations":[],"initialState":{"affineTransform":[1,0,0,1,0,0],"masksToBounds":false,"rotation":0,"scale":1,"position":{"pointX":512,"pointY":384},"width":1024,"sublayerTransform":[1,0,0,0,0,1,0,0,0,0,1,0,0,0,0,1],"contentsRect":{"y":0,"x":0,"width":1,"height":1},"opacity":1,"edgeAntialiasingMask":251658240,"height":768,"hidden":false,"anchorPoint":{"pointX":0.5,"pointY":0.5}},"objectID":"0","layers":[{"animations":[],"initialState":{"affineTransform":[1,0,0,1,0,0],"masksToBounds":false,"rotation":0,"scale":1,"position":{"pointX":512,"pointY":384},"width":1024,"sublayerTransform":[1,0,0,0,0,1,0,0,0,0,1,-0.00049229876906403734,0,0,0,1],"contentsRect":{"y":0,"x":0,"width":1,"height":1},"opacity":1,"edgeAntialiasingMask":251658240,"height":768,"hidden":false,"anchorPoint":{"pointX":0.5,"pointY":0.5}},"layers":[{"animations":[],"layers":[],"texturedRectangle":{"isBackgroundTexture":false,"singleTextureOpacity":1,"textureType":0,"textBaseline":0,"textXHeight":0,"isVerticalText":false},"initialState":{"affineTransform":[1,0,0,1,0,0],"masksToBounds":false,"rotation":0,"scale":1,"position":{"pointX":512,"pointY":384},"width":1024,"sublayerTransform":[1,0,0,0,0,1,0,0,0,0,1,0,0,0,0,1],"contentsRect":{"y":0,"x":0,"width":1,"height":1},"opacity":1,"edgeAntialiasingMask":0,"height":768,"hidden":false,"anchorPoint":{"pointX":0.5,"pointY":0.5}},"texture":"F3F263C7AEB6F14214956C86E2AD6C55"}]}]}}]}